pandas_gbq_magic/__init__.py
pandas_gbq_magic/magic.py
pandas_gbq_magic-1.1.2.dist-info/LICENSE.txt
pandas_gbq_magic-1.1.2.dist-info/METADATA
pandas_gbq_magic-1.1.2.dist-info/WHEEL
pandas_gbq_magic-1.1.2.dist-info/top_level.txt
pandas_gbq_magic-1.1.2.dist-info/RECORD
