Metadata-Version: 2.1
Name: pandas-gbq-magic
Version: 1.1.2
Summary: The package provides as magic on top of Pandas GBQ to make querying in Jupter envioronment easy and user  friendly
Home-page: https://github.com/PulakSachdeva52/Big-Query-Magic/
Author: Pulak JS
Author-email: pulaksachdeva@gmail.com
Project-URL: Bug Tracker, https://github.com/PulakSachdeva52/Big-Query-Magic/issues
Classifier: Programming Language :: Python :: 3
Requires-Python: >=3.6
License-File: LICENSE.txt
